Metadata-Version: 2.1
Name: pyxreser
Version: 1.0.0
Summary: pyxreser is a small Python library designed to simplify the creation of Pyxel images by converting 256x256 pixel 15-color PNG or JPG images into .pyxres files.
Home-page: https://github.com/afi-dev/pyxreser
Author: afi-dev
Author-email: aconique@gmail.com
License: LICENSE
Project-URL: Bug Reports, https://github.com/afi-dev/pyxreser/issues
Project-URL: Feature request, https://github.com/afi-dev/pyxreser/issues
Project-URL: Ko-fi, https://ko-fi.com/afidev
Project-URL: Buy me a coffee, https://www.buymeacoffee.com/afidev
Project-URL: Documentation, https://github.com/afi-dev/pyxreser/blob/main/README.md
Project-URL: Source, https://github.com/afi-dev/pyxreser
Project-URL: Changelog, https://github.com/afi-dev/pyxreser/blob/main/CHANGELOG.md
Keywords: python pyxel pyxreser pyxres image converter color png jpg
Classifier: License :: OSI Approved :: MIT License
Classifier: Natural Language :: English
Classifier: Intended Audience :: Developers
Classifier: Development Status :: 5 - Production/Stable
Classifier: Programming Language :: Python :: 3
Requires-Python: >=3.0
License-File: LICENSE
License-File: LICENSE.txt
